requests_utils.py
universities_api.py
universities_exercise_api_v1-0.0.4.dist-info/LICENSE.txt
universities_exercise_api_v1-0.0.4.dist-info/METADATA
universities_exercise_api_v1-0.0.4.dist-info/WHEEL
universities_exercise_api_v1-0.0.4.dist-info/top_level.txt
universities_exercise_api_v1-0.0.4.dist-info/RECORD
