Metadata-Version: 2.1
Name: universities-exercise-api-v1
Version: 0.0.4
Summary: A simple api for working with universities data
Home-page: https://github.com/omerl2322/pip_package_exercise
Author: Omer Levy
Author-email: omerl2322@gmail.com
License: MIT
Platform: UNKNOWN
Classifier: Programming Language :: Python :: 3
Classifier: Programming Language :: Python :: 3.6
Classifier: Programming Language :: Python :: 3.8
Classifier: License :: OSI Approved :: MIT License
Classifier: Operating System :: OS Independent
Requires-Dist: requests (>=2.25.1)
